langchain_voyageai/__init__.py
langchain_voyageai/embeddings.py
langchain_voyageai/py.typed
langchain_voyageai/rerank.py
gigachain_voyageai-0.1.1.dist-info/LICENSE
gigachain_voyageai-0.1.1.dist-info/METADATA
gigachain_voyageai-0.1.1.dist-info/WHEEL
gigachain_voyageai-0.1.1.dist-info/RECORD
